{
  "六星绰号_来源": {
    "银灰": "银老板 | 老板 | 丹增本体 | 前夫哥 | 真男人斩 | 喀兰贸易公司老板身份；丹增是银灰肩上的鸟，银灰80%伤害是丹增打的",
    "艾雅法拉": "小羊 | 羊 | 火山羊 | 奶羊 | 火山 | 名字谐音+可爱形象；奶羊指精二后医疗能力增强",
    "伊芙利特": "小火龙 | 龙 | 龙龙 | 伊芙龙 | 简称小火龙，种族是龙",
    "能天使": "阿能 | 阿噗噜派 | 苹果派 | 能天使 | 阿噗噜派来自技能语音 Apple pie",
    "塞雷娅": "塞爹 | 爹 | 钙质 | 奶盾 | 塞妈 | 强力辅助被称为爹级存在；钙质来自技能钙质化",
    "安洁莉娜": "杰哥 | 洁哥 | 反重力 | 安洁 | 简称谐音；技能反重力模式",
    "史尔特尔": "42姐 | 42 | 莱万汀 | 干员编号42；",
    "斯卡蒂": "虎鲸 | 蒂蒂 | 大红花 | 忧郁蓝调老大 | 大腿夹剑 | 蓝蒂 | 先蒂 | 种族是虎鲸；三技能涌潮悲歌谐音超勇悲歌",
    "陈": "陈sir | 陈警官 | 粉肠龙 | 赤鞘红中 | 拔刀陈 | 剑陈 | 粤语sir；鞘中赤红从左往右读变成赤鞘红中",
    "煌": "猫猫 | 大猫猫 | 基石1.0 | 群挂机 | 煌猫 | 种族是猫；二技能挂机用法；基石干员系列第一位",
    "棘刺": "基石2.0 | 单基石 | 鸡翅 | 海胆 | 基石干员系列第二位；棘刺谐音",
    "山": "基石3.0 | 冲锋山 | 摔炮山 | 白虎 | 基石干员系列第三位",
    "赫拉格": "老爷子 | 赫爷 | 将军 | 角色设定是老将军",
    "拉普兰德": "拉狗 | 沉默狗 | 德克萨斯做得到吗 | 简称；天赋精神摧毁可沉默敌人",
    "德克萨斯": "德狗 | 脆皮狗 | 德克萨斯 | 原型是狼，玩家喜欢用狗称呼",
    "白面鸮": "白咕咕 | 白咕 | 白面咕 | 白村姑 | 充电咕 | 简称；面朝上部署时背面像村姑",
    "莫斯提马": "小莫 | 忧郁蓝调垫底 | 波纹斩 | 莫斯提马 | 三技能序时之匙波纹斩；忧郁蓝调系列",
    "阿米娅": "驴 | 兔兔 | 小驴子 | 大女儿 | 剑兔 | 阿米驴 | 形象像驴；官方也用兔兔自称",
    "华法琳": "ff0 | 法法琳 | 佛法琳 | 华法琳 | 简称ff0；华和法易混淆",
    "麦哲伦": "麦麦 | 小企鹅 | 麦哲伦 | 召唤无人机战斗",
    "梅菲斯特": "梅菲 | 牧群 | 梅妃 | 罚站梅 | 简称；5-10罚站Boss",
    "W": "旺盆栽 | 搅屎棍 | W | 精二立绘像旺仔",
    "傀影": "影子 | 紫可乐 | 影子哥 | 召唤影子协同作战",
    "迷迭香": "小猫猫 | 肉丝 | 小女儿 | 迷老师 | 形象可爱像小猫",
    "温蒂": "水熊虫 | 后蒂 | 推击手；水熊虫生命力顽强",
    "铃兰": "小狐狸 | 狐萝卜 | 光 | 种族是狐狸",
    "年": "六星奶 | 年姐姐 | 六星医疗",
    "令": "令姐 | 龙令 | 召唤令 | 召唤系干员",
    "水月": "水产品 | 深蓝之子 | 集成战略水月与深蓝之树主题",
    "缄默德克萨斯": "异德 | 宜德 | 异格W | 德克萨斯异格形态",
    "百炼嘉维尔": "异嘉 | 宜家 | 嘉百练 | 百嘉 | 嘉维尔异格形态；缩写异嘉谐音宜家",
    "艾丽妮": "鲸鱼 | 小鸟 | 种族是鲸鱼",
    "玛恩纳": "叔叔 | 玛恩纳叔叔 | 叔叔 | 干员语音中博士称其为叔叔",
    "重岳": "拳皇 | 孔子 | 武人近卫；攻击方式像拳击",
    "焰影苇草": "焰苇 | 苇草异格形态",
    "SP临光": "耀骑士 | 奶临 | 耀临光 | 174 | 临光异格；医疗类型",
    "纯烬艾雅法拉": "纯羊 | 奶羊 | 小羊异格形态；行医分支",
    "风笛": "冲锋王 | 风笛 | 冲锋手先锋；落地立即开技能",
    "推进之王": "椰子 | 王小姐 | 推王 | 立绘形象像椰子",
    "琴柳": "太阳花 | 贞德 | 76 | 执旗手分支",
    "鸿雪": "打字机 | 狙击干员；攻击像打字",
    "伊内丝": "跑路 | 伊内丝 | 情报官分支；高机动性",
    "老鲤": "鲤 | 老鲤 | 六星干员",
    "维什戴尔": "ew | 异格W | 维什戴尔 | 维什戴尔是干员W的异格，ew是异W的谐音",
    "焰尾": "小松鼠 | 红松骑士团团长+原型为红松鼠",
    "嵯峨": "纳豆干饭 | 小僧 | 战斗语音会喊纳豆拌饭",
    "灰烬": "Ash | 英文代号Ash",
    "早露": "枣子姐 | 强度问题+早与枣谐音",
    "远牙": "远呀 | 谐音+技能射程极长",
    "空弦": "三弦 | 谐音空弦为三弦",
    "刻俄柏": "小刻 | 傻狗 | 刻狗 | 六星术师",
    "异客": "考哥 | 神 | 强度问题+电竞圈Uzi梗",
    "夕": "画师 | 夕是画家，能召唤画中生物小自在",
    "卡涅利安": "卡子 | 卡子姐 | 代号谐音",
    "凯尔希": "太后 | 前妻 | 凯太后 | 剧情身份",
    "夜莺": "白恶魔 | 对比闪灵的黑恶魔",
    "闪灵": "黑恶魔 | 对比夜莺的白恶魔",
    "浊心斯卡蒂": "红蒂 | 异格形态+红色主题",
    "歌蕾蒂娅": "哥蒂 | 代号Gladiia谐音",
    "归溟幽灵鲨": "归溟 | 幽灵鲨异格形态",
    "星熊": "星能 | 鬼姐 | 电风扇 | 星能是形近字；电风扇来自三技能",
    "森蚺": "祖玛玛 | 本名祖玛玛，来源于阿兹特克文化",
    "帕拉斯": "牛牛 | 原型为水牛+技能语音空耳",
    "羽毛笔": "二女儿 | 剧情中地位",
    "鞭刃": "姑妈 | 剧情身份",
    "断崖": "王之力 | 声优梗",
    "芙兰卡": "胖狐狸 | 身材丰满且原型为狐狸",
    "惊蛰": "雷子姐 | 五星术师，链术师，英文名Leizi谐音+使用雷电攻击",
    "极境": "鸡精 | 谐音",
    "夜半": "半夜 | 眠兽 | 五星先锋",
    "格拉尼": "小马 | 原型为马，种族库兰塔",
    "贾维": "javi | 简称",
    "断罪者": "内鬼 | 一拳超人 | 孔雀 | 技能看运气",
    "吽": "hong | 代号谐音轰",
    "狮蝎": "地刺 | 特种干员，伏击客，攻击方式像星际争霸地刺",
    "瑕光": "瑕子姐 | 六星重装，守护者，奶盾",
    "雪雉": "雪鸡 | 捡币鸡 | 五星特种，钩索师，活动赠送"
  },
  "五星绰号_来源": {
    "幽灵鲨": "鲨鲨 | 肉丝 | 代号昵称简称",
    "蓝毒": "脆脆蛙 | 毒蛙 | 蓝莓 | 血防低+种族是蛙",
    "普罗旺斯": "大尾巴狼 | 尾巴狼 | 立绘尾巴很大",
    "杰西卡": "富婆 | 流泪猫猫头 | 猫猫头 | 剧情中买了大量源石子弹",
    "诗怀雅": "叉烧猫 | 叉烧 | 同人作品梗",
    "星极": "D32钢 | 钢丝球 | 精二立绘神似D32钢材料",
    "火神": "公招三幻神 | 公招三幻神之一",
    "因陀罗": "公招三幻神 | 公招三幻神之一",
    "雷蛇": "充电蛇 | 充电能力",
    "天火": "公招三幻神 | 公招三幻神之一",
    "凛冬": "冬将军 | 白帝圣剑 | 战斗语音力量与荣耀空耳",
    "送葬人": "阿葬 | 简称+谐音",
    "陨星": "大甲虫 | 相声三人组 | 攻击动画像甲虫",
    "格劳克斯": "海豚 | 种族是海豚",
    "食铁兽": "熊猫 | 种族是熊猫",
    "嘉维尔": "剪指甲 | 战斗台词让我来给你剪剪指甲",
    "杜宾": "教官 | 剧情身份",
    "泡泡": "钢背兽 | 立绘形象像钢背兽",
    "角峰": "jio峰 | 老妈子 | jio峰是谐音梗，老妈子是因为擅长厨艺",
    "讯使": "香香鹿 | 讯哥儿 | 原型是黑麝，香腺分泌激素有香味",
    "清流": "江豚 | 种族是江豚"
  },
  "四星绰号_来源": {
    "桃金娘": "桃子 | 桃大将军 | 法国人 | 投降先锋 | 执旗手，回费能力强",
    "红豆": "豆子龙 | 赵子豆 | 常山豆子龙 | 击杀回费先锋，强度高",
    "蛇屠箱": "龟龟 | 自闭龟 | 种族是乌龟，防御力极高",
    "古米": "cocodayo | 扣扣打油 | 战斗语音空耳",
    "坚雷": "零食头子 | 负责罗德岛零食分发网络",
    "清道夫": "老鼠 | 立绘原型是老鼠",
    "流星": "刘星 | 《家有儿女》角色名谐音",
    "香草": "小香草 | 四星香草，外号用于区分五星干员",
    "泡普卡": "电锯人 | 鲍勃卡 | 四星近卫，剧情中在伐木场工作",
    "刻刀": "合成玉成精 | 立绘形象像合成玉",
    "豆苗": "豆芽 | 代号谐音",
    "苏苏洛": "冥王星 | 冥土追魂 | 二技能爆发奶，冥王星是谐音",
    "波登可": "波司登 | 方舟关羽 | 名字谐音；立绘像关羽",
    "阿消": "消哥 | 龙门第一rapper | 台词语速极快像rapper；白送的四星推特种",
    "暗索": "窃格瓦拉 | 拉人技能和窃格瓦拉偷电瓶车一样",
    "砾": "石乐 | 代号谐音",
    "缠丸": "傻大姐 | 性格豪爽",
    "慕斯": "猫猫 | 原型是猫",
    "艾丝黛尔": "小鳄鱼 | 原型是鳄鱼"
  },
  "三星绰号_来源": {
    "芬": "芳 | 芬队 | A1预备组队长",
    "玫兰莎": "玫剑圣 | 三星战神，空降绝食",
    "安塞尔": "猛男 | 立绘形象高大健壮",
    "克洛丝": "KKDY | 克天使 | co~co~da~yo~ | 放置时有可爱音效",
    "翎羽": "鲮鱼 | 小羽毛 | 原型是鲮鱼，种族黎博利",
    "斑点": "斑点 | 奶盾 | 三星奶盾，阻挡回血",
    "米格鲁": "格莫拉 | 外号谐音"
  },
  "二星绰号_来源": {
    "夜刀": "夜刀神 | 二星快速复活",
    "杜林": "杜林 | 秃头 | 摸鱼王 | 二星术士，因立绘问题被称秃头",
    "12F": "12F | 闪避达人 | 二星术士，有50%物理闪避"
  },
  "一星绰号_来源": {
    "Castle-3": "近卫小车 | 城堡3 | CASTLE | 一星近卫支援机械，不受部署数量限制",
    "Lancet-2": "医疗小车 | 馒头 | 一星医疗支援机械，不受部署数量限制",
    "THRM-EX": "特种小车 | 自爆小车 | 热exa | 一星特种支援机械，不受部署数量限制，3秒后自爆"
  },
  "游戏术语": {
    "刮痧": "形容输出太低，伤害像刮痧一样",
    "抄作业": "参考其他玩家的通关阵容/打法",
    "搓玉": "通过基建刷合成玉",
    "白嫖": "不损失干员击杀敌人",
    "打年糕": "阻挡+治疗慢慢磨死敌人",
    "罚站": "让敌人站在原地不动或干员不攻击",
    "充电宝": "能给队友回技力的干员",
    "工具人": "基建专用的低练度干员",
    "抛光": "敌人血量没掉多少",
    "漏怪": "没有阻挡住敌人让敌人通过",
    "堵门": "在门口阻挡所有敌人",
    "摔炮": "快速部署然后撤退的用法",
    "决战技": "一次性大量伤害的技能",
    "基石干员": "可以稳定站场输出的干员",
    "三幻神": "开服四大幻神：能天使、银灰、小羊、小火龙",
    "高资": "公开招募高级资深干员标签",
    "双快活": "两个快速复活特种配合",
    "真男人斩": "银灰的真银斩",
    "火山": "艾雅法拉的三技能",
    "精神摧毁": "拉普兰德的天赋，可沉默敌人",
    "单奶": "单体治疗技能",
    "群奶": "群体治疗技能",
    "对空狙": "专门针对飞行敌人的狙击干员",
    "速狙": "快速攻击的狙击干员",
    "群狙": "攻击多个目标的狙击干员",
    "法蒸": "法术蒸发，法师秒杀敌人",
    "物蒸": "物理蒸发，物理伤害秒杀敌人",
    "对策卡": "针对特定敌人或机制的干员",
    "人权卡": "必须拥有的强力干员",
    "幻神": "极其强力的干员",
    "对策": "针对特定关卡的策略",
    "摆完挂机": "摆好阵型后挂机自动通关",
    "玉": "合成玉，用于抽卡",
    "石": "源石，用于购买体力或皮肤",
    "井": "300抽保底换取限定干员",
    "抽卡": "使用源石或合成玉获取干员",
    "公招": "公开招募，使用标签获取干员",
    "公招计算器": "计算公开招募标签组合的工具",
    "肉鸽": "集成战略Roguelike模式",
    "水月肉鸽": "集成战略第二期",
    "傀影肉鸽": "集成战略第一期",
    "熔炉还魂记": "集成战略第三期",
    "危机合约": "高难限时活动",
    "SSS": "危机合约赛季关卡",
    "保全派驻": "一种游戏模式",
    "生息演算": "限时活动",
    "揭幕者们": "2024感谢庆典活动",
    "泰拉大地调查": "2024年活动",
    "寻昼行动": "2024年活动"
  },
  "明日方舟术语": {
    "Ave Mujica": "包括丰川祥子、八幡海铃、三角初华、祐天寺若麦、若叶睦",
    "Fever": "Fever累计至450点时，任意一位Ave Mujica成员手动触发技能后，在场所有Ave Mujica成员20秒内会持续释放当前技能",
    "业报": "每当加工心情消耗8的配方未产出副产品时，所消耗的每1点心情转化为1点业报",
    "人间烟火": "可影响巫术结晶相关技能",
    "伤害减免": "受到的伤害降低一定数值",
    "侵蚀损伤": "侵蚀损伤累计至1000时，永久降低100点防御力并受到800点物理伤害",
    "侵蚀损伤·我方": "累计满时爆发，敌人立即受到5000点元素伤害且永久降低120点防御力",
    "停顿": "移动速度降低80%",
    "偷取": "减少目标的基础属性作为自身加成",
    "元素损伤": "包括神经损伤、侵蚀损伤、灼燃损伤、凋亡损伤",
    "元素脆弱": "受到的元素伤害提升相应比例",
    "其他设施": "除特定设施外的其他设施",
    "冻结": "无法移动、攻击及使用技能",
    "凋亡损伤": "凋亡损伤累计至1000时，15秒内无法开启技能，每秒损失1点技力并受到100点法术伤害",
    "凋亡损伤·我方": "累计满时爆发，使敌人附加50%虚弱但期间逐渐恢复，每秒受到800点元素伤害",
    "吟唱": "停止攻击一段时间后尝试开启技能，期间被打断则中止",
    "因果": "每当加工心情消耗4以下的配方未产出副产品时，所消耗的每1点心情转化为1点因果",
    "坚忍": "根据已损失的生命值获得相应比例的属性加成",
    "外势": "由以下干员的基建技能提供望每有一间贸易站、发电站，外势+1",
    "失重": "重量下降一个等级",
    "寒冷": "攻击速度下降30，如果在持续时间内再次受到寒冷效果则会变为冻结",
    "小节": "可影响感知信息相关变量",
    "屏障": "可以吸收一定数值的伤害",
    "工作场所": "进行工作的设施",
    "庇护": "受到的物理和法术伤害降低相应比例",
    "异常状态": "包括晕眩、寒冷、冻结等",
    "弱点伤害": "造成物理或法术伤害时，根据目标防御力和法术抗性变更伤害类型",
    "心情落差": "干员自身心情上限与当前心情值的差值",
    "思维链环": "可影响念力、意识实体相关技能",
    "恐惧": "无法被阻挡并四散逃跑",
    "感知信息": "可影响思维链环、无声共鸣相关变量",
    "战栗": "被阻挡后无法进行普通攻击",
    "折射": "生效时，法术抗性+70",
    "护盾": "每层护盾可以抵挡一次伤害",
    "抵抗": "晕眩、寒冷、冻结等负面状态的持续时间减半，麻痹等效果每5秒流失1层",
    "持续攻击": "无论攻击范围内是否有攻击目标，都会持续进行攻击",
    "损伤屏障": "可以吸收一定数值的元素损伤",
    "无声共鸣": "可影响徘徊旋律、怅惘和声、无词颂歌相关技能",
    "晕眩": "无法移动、阻挡、攻击及使用技能",
    "束缚": "无法移动",
    "梦境": "可影响感知信息相关变量",
    "武道协助": "专精训练至1级时累计1点、2级时累计2点、3级时累计3点，累计上限为3点",
    "沉睡": "无敌且无法行动",
    "法术脆弱": "受到的法术伤害提升相应比例",
    "浮空": "变为空中单位，无法移动、攻击及使用技能",
    "灼燃损伤": "灼燃损伤累计至1000时，10秒内降低20法术抗性并受到1200点法术伤害",
    "灼燃损伤·我方": "累计满时爆发，敌人立即受到7000点元素伤害且期间法术抗性-20",
    "物理护盾": "每层物理护盾可以抵挡一次物理伤害",
    "物理脆弱": "受到的物理伤害提升相应比例",
    "神经损伤": "神经损伤累计至1000时，受到1000点真实伤害并晕眩10秒",
    "神经损伤·我方": "累计满时爆发，敌人立即受到6000点元素伤害且获得3层麻痹",
    "移动": "不退场，以当前血量在目标位置部署",
    "精力充沛": "生命值高于一定比例时获得一定属性加成",
    "绑定": "绑定对象不在场时技能强制结束，清空所有技力且无法回复技力",
    "脆弱": "受到的物理、法术、真实伤害提升相应比例",
    "蓄力": "技力达到上限可继续回复，回复至上限2倍时进入蓄力状态",
    "虚弱": "使目标攻击力降低相应比例",
    "补弹": "为其他人的弹药类技能补充弹药",
    "装备应变": "选中在场干员后，可以通过一定条件激活的额外效果",
    "记忆碎片": "可影响感知信息相关变量",
    "诱导": "无法被阻挡并向目标位置移动",
    "起飞": "不阻挡地面敌人且不会被地面敌人攻击，可以阻挡飞行敌人",
    "过载": "技能持续拥有两段计量槽，技能进行到一半时触发额外效果",
    "近地悬浮": "无法被阻挡或近战攻击",
    "进攻方": "在某些游戏模式中代表进攻方",
    "迷彩": "不阻挡时不成为敌方普通攻击的目标",
    "重伤": "移速下降且无法被阻挡，10秒后自然死亡，被击杀后使击杀者回复数点技力",
    "隐匿": "不阻挡时不成为敌方攻击的目标",
    "魔力": "特殊技力，整场战斗继承",
    "麻痹": "每层麻痹可以使敌人在普通攻击时打断本次攻击，上限3层",
    "鼓舞": "获得额外附加的基础属性加成"
  },
  "剧情梗_来源": {
    "巴别塔恶灵": "W对博士的称呼",
    "博士生导师": "制作攻略的大佬",
    "白帝圣剑": "凛冬战斗语音空耳",
    "不要恐慌": "4-4关卡名+迫害弑君者",
    "丢人给我退出战场": "凛冬失败台词",
    "刀客塔": "博士Doctor的音译",
    "42星干员": "可露希尔人设图标了42颗星",
    "力量与荣耀": "凛冬战斗语音",
    "让我来给你剪剪指甲": "嘉维尔战斗台词",
    "co~co~da~yo~": "克洛丝放置音效空耳",
    "电锯人": "泡普卡在伐木场工作",
    "王之力": "断崖声优梗"
  },
  "抽卡梗_含义": {
    "沉船": "抽卡歪了，没出货",
    "被XX拉黑": "长期抽不到某个干员",
    "单抽出货": "单抽就抽到",
    "井": "300抽保底井限定干员",
    "十连出金": "十连抽获得六星干员",
    "限定": "限时UP的干员",
    "非酋": "运气极差的玩家",
    "欧皇": "运气极好的玩家",
    "保底": "必定获得的最低奖励",
    "歪": "抽到了其他干员而非期望的",
    "定向": "定向寻访选择特定干员",
    "资源 expend": "消耗大量资源抽卡",
    "648": "充值档位，指代重氪",
    "648沉船": "充648元还沉船"
  },
  "基建梗_含义": {
    "996工具人": "基建工具人",
    "搓玉": "生产源石碎片换合成玉",
    "制造站": "基建中制造作战物资的建筑",
    "贸易站": "基建中换取龙门币的建筑",
    "发电站": "基建中提供订单预约的建筑",
    "宿舍": "基建中恢复干员心情的建筑",
    "会客室": "基建中获取线索的建筑",
    "加工站": "基建中加工材料的建筑",
    "无人机": "基建中加速生产的消耗品",
    "订单": "贸易站完成的任务"
  },
  "活动梗_来源": {
    "危机合约": "高难活动",
    "31封神": "光谱行动新约31级为实操封顶",
    "集成战略": "Roguelike玩法",
    "水月与深蓝之树": "集成战略第二期主题",
    "傀影与猩红孤钻": "集成战略第一期主题",
    "熔炉还魂记": "集成战略第三期主题",
    "揭幕者们": "2024感谢庆典SideStory",
    "彩车游行": "2024感谢庆典活动关卡",
    "泰拉大地调查": "SideStory活动",
    "寻昼行动": "危机合约#8赛季",
    "光谱行动": "危机合约赛季",
    "利卡遗骨": "危机合约赛季词缀",
    "生息演算": "限时活动",
    "感谢庆典": "年度大型活动",
    "愚人节": "官方整活活动",
    "四月辑录": "愚人节活动合集"
  },
  "近期梗_来源": {
    "仙术杯": "玩家组织的娱乐赛事",
    "划火柴": "同帧部署/0帧部署干员的高难操作技巧，暂停后快速拖放干员",
    "左手席": "仙术杯解说席",
    "插U盘": "仙术杯比赛中的操作",
    "妮芙充满了决心": "UT梗改自这使你充满了决心",
    "限定五星级": "指限定干员",
    "2024感谢庆典": "年度大型活动",
    "绝悟": "危机合约主题",
    "松烟行动": "危机合约赛季"
  },
  "干员组合_成员_来源": {
    "三幻神": "能天使 银灰 艾雅法拉 伊芙利特 | 开服四大幻神",
    "基石干员": "煌 棘刺 山 泥岩 | 版本强势地面输出干员，可挂机单守一路",
    "公招三幻神": "Castle-3 火神 因陀罗 天火 | 只能公招募获取且难出",
    "企鹅物流": "能天使 德克萨斯 拉普兰德 空 | 企鹅物流公司成员",
    "忧郁蓝调": "斯卡蒂 陈 莫斯提马 | 立绘色调偏蓝且强度递减",
    "的女儿": "阿米娅 迷迭香 羽毛笔 | 剧情中被博士称为女儿",
    "黑白恶魔": "夜莺 闪灵 | 白恶魔夜莺，黑恶魔闪灵",
    "相声三人组": "雷蛇 芙兰卡 陨星 | 经常一起出现",
    "深海猎人": "斯卡蒂 歌蕾蒂娅 幽灵鲨 格劳克斯 | 深海猎人组织",
    "喀兰贸易": "银灰 崖心 初雪 | 喀兰贸易公司",
    "罗小黑": "罗小黑 BL 小黑 | 联动干员"
  }
}